<?xml version="1.0" encoding="utf-8"?>
<clothing-items>
 <clothing>
  <id>
   578457649
  </id>
  <name>
   Vans Shoes I-7496
  </name>
  <category>
   Shoes
  </category>
  <size>
   XXL
  </size>
  <color>
   Синий
  </color>
  <material>
   Лен
  </material>
  <price>
   630958
  </price>
  <rating>
   4.84
  </rating>
  <reviews>
   231125
  </reviews>
  <sporty>
   no
  </sporty>
 </clothing>
 <clothing>
  <id>
   586423092
  </id>
  <name>
   Vans Shirt L-4139
  </name>
  <category>
   Shirt
  </category>
  <size>
   M
  </size>
  <color>
   Желтый
  </color>
  <material>
   Вискоза
  </material>
  <price>
   396007
  </price>
  <rating>
   4.33
  </rating>
  <reviews>
   792812
  </reviews>
  <new>
   +
  </new>
  <exclusive>
   yes
  </exclusive>
  <sporty>
   no
  </sporty>
 </clothing>
 <clothing>
  <id>
   228253723
  </id>
  <name>
   Converse Pants C-5121
  </name>
  <category>
   Pants
  </category>
  <size>
   XXL
  </size>
  <color>
   Зеленый
  </color>
  <material>
   Полиэстер
  </material>
  <price>
   204088
  </price>
  <rating>
   3.64
  </rating>
  <reviews>
   479524
  </reviews>
  <exclusive>
   no
  </exclusive>
  <sporty>
   no
  </sporty>
 </clothing>
 <clothing>
  <id>
   416915128
  </id>
  <name>
   DC Belts G-5302
  </name>
  <category>
   Belts
  </category>
  <size>
   XXL
  </size>
  <color>
   Красный
  </color>
  <material>
   Шерсть
  </material>
  <price>
   958682
  </price>
  <rating>
   3.29
  </rating>
  <reviews>
   696365
  </reviews>
  <new>
   +
  </new>
  <sporty>
   yes
  </sporty>
 </clothing>
 <clothing>
  <id>
   880636983
  </id>
  <name>
   Converse Jeans Q-2336
  </name>
  <category>
   Jeans
  </category>
  <size>
   XL
  </size>
  <color>
   Синий
  </color>
  <material>
   Шерсть
  </material>
  <price>
   653660
  </price>
  <rating>
   3.13
  </rating>
  <reviews>
   643366
  </reviews>
  <exclusive>
   yes
  </exclusive>
 </clothing>
 <clothing>
  <id>
   464894078
  </id>
  <name>
   DC Shoes Z-8624
  </name>
  <category>
   Shoes
  </category>
  <size>
   XXL
  </size>
  <color>
   Желтый
  </color>
  <material>
   Кожа
  </material>
  <price>
   289849
  </price>
  <rating>
   1.79
  </rating>
  <reviews>
   727214
  </reviews>
  <new>
   +
  </new>
  <sporty>
   yes
  </sporty>
 </clothing>
 <clothing>
  <id>
   131264913
  </id>
  <name>
   New Balance Handbags F-4705
  </name>
  <category>
   Handbags
  </category>
  <size>
   S
  </size>
  <color>
   Фиолетовый
  </color>
  <material>
   Вискоза
  </material>
  <price>
   428580
  </price>
  <rating>
   2.52
  </rating>
  <reviews>
   150654
  </reviews>
  <new>
   +
  </new>
  <exclusive>
   no
  </exclusive>
 </clothing>
 <clothing>
  <id>
   706625181
  </id>
  <name>
   PleinSport Belts O-3863
  </name>
  <category>
   Belts
  </category>
  <size>
   L
  </size>
  <color>
   Оранжевый
  </color>
  <material>
   Нейлон
  </material>
  <price>
   836300
  </price>
  <rating>
   3.71
  </rating>
  <reviews>
   218905
  </reviews>
  <new>
   +
  </new>
 </clothing>
 <clothing>
  <id>
   859958066
  </id>
  <name>
   Vans Pants C-8845
  </name>
  <category>
   Pants
  </category>
  <size>
   XXL
  </size>
  <color>
   Желтый
  </color>
  <material>
   Хлопок
  </material>
  <price>
   525938
  </price>
  <rating>
   4.01
  </rating>
  <reviews>
   976212
  </reviews>
  <exclusive>
   yes
  </exclusive>
  <sporty>
   no
  </sporty>
 </clothing>
 <clothing>
  <id>
   994890142
  </id>
  <name>
   Converse Umbrellas Y-1397
  </name>
  <category>
   Umbrellas
  </category>
  <size>
   XL
  </size>
  <color>
   Фиолетовый
  </color>
  <material>
   Полиэстер
  </material>
  <price>
   221257
  </price>
  <rating>
   4.74
  </rating>
  <reviews>
   470152
  </reviews>
  <sporty>
   no
  </sporty>
 </clothing>
 <clothing>
  <id>
   996667829
  </id>
  <name>
   Lacoste Blouse C-4968
  </name>
  <category>
   Blouse
  </category>
  <size>
   L
  </size>
  <color>
   Желтый
  </color>
  <material>
   Лен
  </material>
  <price>
   907798
  </price>
  <rating>
   1.03
  </rating>
  <reviews>
   393998
  </reviews>
  <new>
   -
  </new>
  <exclusive>
   no
  </exclusive>
  <sporty>
   no
  </sporty>
 </clothing>
 <clothing>
  <id>
   518511965
  </id>
  <name>
   Asics Handbags E-2579
  </name>
  <category>
   Handbags
  </category>
  <size>
   XL
  </size>
  <color>
   Голубой
  </color>
  <material>
   Вискоза
  </material>
  <price>
   768210
  </price>
  <rating>
   2.64
  </rating>
  <reviews>
   161596
  </reviews>
  <new>
   -
  </new>
  <exclusive>
   no
  </exclusive>
 </clothing>
 <clothing>
  <id>
   754802432
  </id>
  <name>
   Fila Shirt A-1552
  </name>
  <category>
   Shirt
  </category>
  <size>
   XXL
  </size>
  <color>
   Фиолетовый
  </color>
  <material>
   Хлопок
  </material>
  <price>
   284245
  </price>
  <rating>
   3.26
  </rating>
  <reviews>
   702322
  </reviews>
  <new>
   +
  </new>
 </clothing>
 <clothing>
  <id>
   493753624
  </id>
  <name>
   Vans Shirt T-2130
  </name>
  <category>
   Shirt
  </category>
  <size>
   M
  </size>
  <color>
   Фиолетовый
  </color>
  <material>
   Лен
  </material>
  <price>
   182705
  </price>
  <rating>
   1.36
  </rating>
  <reviews>
   127575
  </reviews>
  <new>
   -
  </new>
  <sporty>
   yes
  </sporty>
 </clothing>
 <clothing>
  <id>
   424512704
  </id>
  <name>
   Nike Sweater V-5359
  </name>
  <category>
   Sweater
  </category>
  <size>
   L
  </size>
  <color>
   Голубой
  </color>
  <material>
   Шерсть
  </material>
  <price>
   788034
  </price>
  <rating>
   1.76
  </rating>
  <reviews>
   566108
  </reviews>
  <new>
   -
  </new>
 </clothing>
 <clothing>
  <id>
   154921783
  </id>
  <name>
   Vans Sweater Y-1978
  </name>
  <category>
   Sweater
  </category>
  <size>
   L
  </size>
  <color>
   Зеленый
  </color>
  <material>
   Кожа
  </material>
  <price>
   755109
  </price>
  <rating>
   4.12
  </rating>
  <reviews>
   38777
  </reviews>
  <new>
   -
  </new>
  <exclusive>
   yes
  </exclusive>
  <sporty>
   no
  </sporty>
 </clothing>
 <clothing>
  <id>
   960155162
  </id>
  <name>
   Adidas Pants U-5106
  </name>
  <category>
   Pants
  </category>
  <size>
   XL
  </size>
  <color>
   Оранжевый
  </color>
  <material>
   Хлопок
  </material>
  <price>
   931972
  </price>
  <rating>
   1.97
  </rating>
  <reviews>
   124165
  </reviews>
  <new>
   -
  </new>
  <exclusive>
   no
  </exclusive>
  <sporty>
   yes
  </sporty>
 </clothing>
 <clothing>
  <id>
   483154675
  </id>
  <name>
   Addidas Shirt T-5276
  </name>
  <category>
   Shirt
  </category>
  <size>
   XL
  </size>
  <color>
   Желтый
  </color>
  <material>
   Хлопок
  </material>
  <price>
   689358
  </price>
  <rating>
   2.2
  </rating>
  <reviews>
   893655
  </reviews>
  <new>
   +
  </new>
  <exclusive>
   yes
  </exclusive>
  <sporty>
   yes
  </sporty>
 </clothing>
</clothing-items>
