<?xml version="1.0" encoding="utf-8"?>
<clothing-items>
 <clothing>
  <id>
   661718407
  </id>
  <name>
   Under Armour Socks C-1441
  </name>
  <category>
   Socks
  </category>
  <size>
   M
  </size>
  <color>
   Голубой
  </color>
  <material>
   Лен
  </material>
  <price>
   154069
  </price>
  <rating>
   3.71
  </rating>
  <reviews>
   172916
  </reviews>
  <new>
   +
  </new>
  <exclusive>
   no
  </exclusive>
  <sporty>
   yes
  </sporty>
 </clothing>
 <clothing>
  <id>
   570814299
  </id>
  <name>
   Under Armour Jeans G-1203
  </name>
  <category>
   Jeans
  </category>
  <size>
   XXL
  </size>
  <color>
   Желтый
  </color>
  <material>
   Шерсть
  </material>
  <price>
   164400
  </price>
  <rating>
   1.36
  </rating>
  <reviews>
   738198
  </reviews>
  <new>
   -
  </new>
  <sporty>
   no
  </sporty>
 </clothing>
 <clothing>
  <id>
   454683498
  </id>
  <name>
   Vans Pants D-3618
  </name>
  <category>
   Pants
  </category>
  <size>
   M
  </size>
  <color>
   Фиолетовый
  </color>
  <material>
   Шерсть
  </material>
  <price>
   709432
  </price>
  <rating>
   3.39
  </rating>
  <reviews>
   626633
  </reviews>
  <new>
   -
  </new>
  <sporty>
   yes
  </sporty>
 </clothing>
 <clothing>
  <id>
   223686427
  </id>
  <name>
   New Balance Shoes J-4594
  </name>
  <category>
   Shoes
  </category>
  <size>
   M
  </size>
  <color>
   Желтый
  </color>
  <material>
   Шерсть
  </material>
  <price>
   713296
  </price>
  <rating>
   4.78
  </rating>
  <reviews>
   846431
  </reviews>
  <sporty>
   yes
  </sporty>
 </clothing>
 <clothing>
  <id>
   970581278
  </id>
  <name>
   Addidas Handbags E-8004
  </name>
  <category>
   Handbags
  </category>
  <size>
   XL
  </size>
  <color>
   Зеленый
  </color>
  <material>
   Нейлон
  </material>
  <price>
   981008
  </price>
  <rating>
   4.42
  </rating>
  <reviews>
   878420
  </reviews>
  <sporty>
   yes
  </sporty>
 </clothing>
 <clothing>
  <id>
   961099881
  </id>
  <name>
   Converse T-shirt F-7180
  </name>
  <category>
   T-shirt
  </category>
  <size>
   M
  </size>
  <color>
   Желтый
  </color>
  <material>
   Шелк
  </material>
  <price>
   330780
  </price>
  <rating>
   4.16
  </rating>
  <reviews>
   447059
  </reviews>
  <exclusive>
   no
  </exclusive>
 </clothing>
 <clothing>
  <id>
   733469359
  </id>
  <name>
   Nike Belts E-5098
  </name>
  <category>
   Belts
  </category>
  <size>
   M
  </size>
  <color>
   Красный
  </color>
  <material>
   Вискоза
  </material>
  <price>
   117179
  </price>
  <rating>
   1.38
  </rating>
  <reviews>
   722224
  </reviews>
  <exclusive>
   yes
  </exclusive>
  <sporty>
   yes
  </sporty>
 </clothing>
 <clothing>
  <id>
   835378108
  </id>
  <name>
   Addidas Shirt B-7873
  </name>
  <category>
   Shirt
  </category>
  <size>
   XXL
  </size>
  <color>
   Желтый
  </color>
  <material>
   Кожа
  </material>
  <price>
   352849
  </price>
  <rating>
   3.38
  </rating>
  <reviews>
   149052
  </reviews>
  <exclusive>
   yes
  </exclusive>
  <sporty>
   no
  </sporty>
 </clothing>
 <clothing>
  <id>
   721607929
  </id>
  <name>
   DC Blouse E-3821
  </name>
  <category>
   Blouse
  </category>
  <size>
   L
  </size>
  <color>
   Оранжевый
  </color>
  <material>
   Вискоза
  </material>
  <price>
   476370
  </price>
  <rating>
   2.13
  </rating>
  <reviews>
   570002
  </reviews>
  <new>
   -
  </new>
  <exclusive>
   no
  </exclusive>
 </clothing>
 <clothing>
  <id>
   769410783
  </id>
  <name>
   Nike Belts N-5693
  </name>
  <category>
   Belts
  </category>
  <size>
   M
  </size>
  <color>
   Синий
  </color>
  <material>
   Шелк
  </material>
  <price>
   740653
  </price>
  <rating>
   3.84
  </rating>
  <reviews>
   777355
  </reviews>
  <new>
   -
  </new>
  <exclusive>
   yes
  </exclusive>
  <sporty>
   no
  </sporty>
 </clothing>
 <clothing>
  <id>
   292804473
  </id>
  <name>
   Brooks Hat D-7026
  </name>
  <category>
   Hat
  </category>
  <size>
   XL
  </size>
  <color>
   Желтый
  </color>
  <material>
   Шелк
  </material>
  <price>
   771015
  </price>
  <rating>
   2.16
  </rating>
  <reviews>
   344590
  </reviews>
  <new>
   -
  </new>
  <exclusive>
   no
  </exclusive>
  <sporty>
   no
  </sporty>
 </clothing>
 <clothing>
  <id>
   713391970
  </id>
  <name>
   PleinSport Handbags J-6343
  </name>
  <category>
   Handbags
  </category>
  <size>
   XXL
  </size>
  <color>
   Красный
  </color>
  <material>
   Кожа
  </material>
  <price>
   470993
  </price>
  <rating>
   2.41
  </rating>
  <reviews>
   33496
  </reviews>
  <new>
   -
  </new>
  <exclusive>
   no
  </exclusive>
  <sporty>
   yes
  </sporty>
 </clothing>
 <clothing>
  <id>
   145237949
  </id>
  <name>
   PleinSport Sweater D-3954
  </name>
  <category>
   Sweater
  </category>
  <size>
   XL
  </size>
  <color>
   Синий
  </color>
  <material>
   Полиэстер
  </material>
  <price>
   278729
  </price>
  <rating>
   4.42
  </rating>
  <reviews>
   371686
  </reviews>
  <sporty>
   no
  </sporty>
 </clothing>
 <clothing>
  <id>
   476677358
  </id>
  <name>
   Vans Handbags U-5146
  </name>
  <category>
   Handbags
  </category>
  <size>
   L
  </size>
  <color>
   Красный
  </color>
  <material>
   Вискоза
  </material>
  <price>
   149510
  </price>
  <rating>
   3.6
  </rating>
  <reviews>
   64962
  </reviews>
  <new>
   +
  </new>
 </clothing>
 <clothing>
  <id>
   130348841
  </id>
  <name>
   Fila T-shirt W-3768
  </name>
  <category>
   T-shirt
  </category>
  <size>
   M
  </size>
  <color>
   Красный
  </color>
  <material>
   Нейлон
  </material>
  <price>
   419285
  </price>
  <rating>
   1.29
  </rating>
  <reviews>
   111046
  </reviews>
  <new>
   -
  </new>
 </clothing>
 <clothing>
  <id>
   795823330
  </id>
  <name>
   Under Armour Jeans O-4949
  </name>
  <category>
   Jeans
  </category>
  <size>
   XL
  </size>
  <color>
   Голубой
  </color>
  <material>
   Кожа
  </material>
  <price>
   536713
  </price>
  <rating>
   2.51
  </rating>
  <reviews>
   740190
  </reviews>
  <new>
   -
  </new>
  <exclusive>
   yes
  </exclusive>
  <sporty>
   yes
  </sporty>
 </clothing>
 <clothing>
  <id>
   330447079
  </id>
  <name>
   Nike Pants B-7809
  </name>
  <category>
   Pants
  </category>
  <size>
   S
  </size>
  <color>
   Оранжевый
  </color>
  <material>
   Кожа
  </material>
  <price>
   951531
  </price>
  <rating>
   3.91
  </rating>
  <reviews>
   984300
  </reviews>
 </clothing>
 <clothing>
  <id>
   248304656
  </id>
  <name>
   Converse Handbags E-1632
  </name>
  <category>
   Handbags
  </category>
  <size>
   XL
  </size>
  <color>
   Голубой
  </color>
  <material>
   Кожа
  </material>
  <price>
   907250
  </price>
  <rating>
   2.09
  </rating>
  <reviews>
   36434
  </reviews>
  <exclusive>
   yes
  </exclusive>
  <sporty>
   yes
  </sporty>
 </clothing>
 <clothing>
  <id>
   941890545
  </id>
  <name>
   Ellesse Gloves C-3625
  </name>
  <category>
   Gloves
  </category>
  <size>
   M
  </size>
  <color>
   Синий
  </color>
  <material>
   Нейлон
  </material>
  <price>
   393134
  </price>
  <rating>
   2.6
  </rating>
  <reviews>
   158657
  </reviews>
  <new>
   -
  </new>
  <exclusive>
   no
  </exclusive>
 </clothing>
 <clothing>
  <id>
   815094472
  </id>
  <name>
   Converse T-shirt D-9593
  </name>
  <category>
   T-shirt
  </category>
  <size>
   L
  </size>
  <color>
   Синий
  </color>
  <material>
   Лен
  </material>
  <price>
   574991
  </price>
  <rating>
   2.33
  </rating>
  <reviews>
   8030
  </reviews>
  <sporty>
   yes
  </sporty>
 </clothing>
 <clothing>
  <id>
   786993323
  </id>
  <name>
   Addidas T-shirt K-4638
  </name>
  <category>
   T-shirt
  </category>
  <size>
   S
  </size>
  <color>
   Оранжевый
  </color>
  <material>
   Лен
  </material>
  <price>
   834771
  </price>
  <rating>
   4.22
  </rating>
  <reviews>
   810332
  </reviews>
  <new>
   -
  </new>
  <exclusive>
   no
  </exclusive>
 </clothing>
 <clothing>
  <id>
   374741843
  </id>
  <name>
   Lacoste Jacket X-2655
  </name>
  <category>
   Jacket
  </category>
  <size>
   S
  </size>
  <color>
   Фиолетовый
  </color>
  <material>
   Шелк
  </material>
  <price>
   547559
  </price>
  <rating>
   4.51
  </rating>
  <reviews>
   734133
  </reviews>
  <exclusive>
   no
  </exclusive>
  <sporty>
   yes
  </sporty>
 </clothing>
 <clothing>
  <id>
   681766295
  </id>
  <name>
   Asics T-shirt O-3076
  </name>
  <category>
   T-shirt
  </category>
  <size>
   L
  </size>
  <color>
   Зеленый
  </color>
  <material>
   Полиэстер
  </material>
  <price>
   830155
  </price>
  <rating>
   3.7
  </rating>
  <reviews>
   396307
  </reviews>
  <new>
   -
  </new>
  <sporty>
   no
  </sporty>
 </clothing>
</clothing-items>
